pythorn/__init__.py
pythorn/algorithms/__init__.py
pythorn/algorithms/dynamic_programming.py
pythorn/algorithms/greedy_algorithm.py
pythorn/algorithms/string_matching.py
pythorn/data_structures/__init__.py
pythorn/data_structures/graphs.py
pythorn/data_structures/linked_list.py
pythorn/data_structures/queue.py
pythorn/data_structures/recursion.py
pythorn/data_structures/searching.py
pythorn/data_structures/sorting.py
pythorn/data_structures/stack.py
pythorn/data_structures/trees.py
pythorn-1.0.0.dist-info/LICENSE
pythorn-1.0.0.dist-info/METADATA
pythorn-1.0.0.dist-info/WHEEL
pythorn-1.0.0.dist-info/top_level.txt
pythorn-1.0.0.dist-info/RECORD
