Metadata-Version: 2.1
Name: pythorn
Version: 1.0.0
Summary: A Python module for all data structures and algorithms.
Home-page: https://github.com/robin025/pythorn
Author: Robin Singh
Author-email: robin25tech@gmail.com
License: MIT
Platform: UNKNOWN
Classifier: Intended Audience :: Education 
Classifier: Intended Audience :: Developers 
Classifier: License :: OSI Approved :: MIT License
Classifier: Programming Language :: Python :: 3
Classifier: Programming Language :: Python :: 3.3
Classifier: Programming Language :: Python :: 3.4
Classifier: Programming Language :: Python :: 3.5
Classifier: Programming Language :: Python :: 3.6
Classifier: Natural Language :: English
Classifier: Operating System :: OS Independent
